{
"hdr": {
    "name": "J1045-4509","freq": "436","site": "parkes","rm": "0","dm": "58.57","scale": "FluxDensity","state": "Intensity","npol": "1","length": "0.00747422","rcvr:name": "","be:name": "",
    "license": "EPN-legacy",
    "ref": {
"shortname":"lor94",
"url":"http://adsabs.harvard.edu/cgi-bin/nph-bib_query?bibcode=1994PhDT.......272 ",
"authors":"Lorimer, D. R.",
"year":"1994",
"title":"PhD thesis, The University of Manchester."
},
    "basename":"lor94_436"
  },
 "files": [
      { "url": "raw_files/lor94/J1045-4509/lor94_436.epn", "format": "EPN" },
      { "url": "psrfits/lor94/J1045-4509/lor94_436.fits", "format": "PSRFITS" },
      { "url": "ascii/lor94/J1045-4509/lor94_436.txt", "format": "Plain Text" }
 ],
  "series": {
  "I":[ [-0.5,0.0853888], [-0.46,0.121673], [-0.42,0], [-0.38,0.00366524], [-0.34,0.0555868], [-0.3,0.0250645], [-0.26,0.00564991], [-0.22,0.0787786], [-0.18,0.213464], [-0.14,0.462188], [-0.1,0.720883], [-0.06,1.0489], [-0.02,0.976842], [0.02,0.665489], [0.06,0.317003], [0.1,0.144961], [0.14,0.07689], [0.18,0.0488805], [0.22,0.0176219], [0.26,0.0683911], [0.3,0.0196066], [0.34,0.0483523], [0.38,0.0574754], [0.42,0.0389091], [0.46,0.0953442]  ],"max":1.0489, "min":0.0
  }
}
